lotsawa/__init__.py
lotsawa/part_of_speech.py
lotsawa/retranslate.py
lotsawa/translate.py
lotsawa/token_classification_config/__init__.py
lotsawa/token_classification_config/part_of_speech.yaml
lotsawa/token_classification_config/help/part-of-speech.yaml
lotsawa/token_classification_config/mode/batch.yaml
lotsawa/token_classification_config/mode/interactive.yaml
lotsawa/token_classification_config/mode/segmenter/model.yaml
lotsawa/token_classification_config/mode/segmenter/target-token-count.yaml
lotsawa/token_classification_config/model/intersyllabic-olive-cormorant.yaml
lotsawa/translation_config/__init__.py
lotsawa/translation_config/retranslate.yaml
lotsawa/translation_config/translate.yaml
lotsawa/translation_config/generation/alphabet-inclusions.yaml
lotsawa/translation_config/generation/fast.yaml
lotsawa/translation_config/generation/medium-beam-long-inputs-pooled-context.yaml
lotsawa/translation_config/generation/medium-beam-long-inputs-retrospective.yaml
lotsawa/translation_config/generation/medium-beam-long-inputs.yaml
lotsawa/translation_config/generation/medium-beam-short-inputs.yaml
lotsawa/translation_config/generation/medium-beam-x2.yaml
lotsawa/translation_config/generation/medium-beam-x3.yaml
lotsawa/translation_config/generation/medium.yaml
lotsawa/translation_config/generation/model-segmenter-pooled-context.yaml
lotsawa/translation_config/generation/slow.yaml
lotsawa/translation_config/help/retranslate.yaml
lotsawa/translation_config/help/translate-research.yaml
lotsawa/translation_config/help/translate.yaml
lotsawa/translation_config/mode/batch.yaml
lotsawa/translation_config/mode/interactive.yaml
lotsawa/translation_config/model/cased.yaml
lotsawa/translation_config/model/nllb-with-context-for-zst.yaml
lotsawa/translation_config/model/nllb-with-context.yaml
lotsawa/translation_config/model/olive-cormorant-bart-pooled-context-cased.yaml
lotsawa/translation_config/model/olive-cormorant-bart-pooled-context.yaml
lotsawa-0.3.4.dist-info/LICENSE
lotsawa-0.3.4.dist-info/METADATA
lotsawa-0.3.4.dist-info/WHEEL
lotsawa-0.3.4.dist-info/entry_points.txt
lotsawa-0.3.4.dist-info/top_level.txt
lotsawa-0.3.4.dist-info/RECORD
