Metadata-Version: 2.1
Name: lotsawa
Version: 0.3.4
Summary: Machine translation and understanding of classical Tibetan
Home-page: https://github.com/compassionai/lotsawa
Author: CompassionAI
Author-email: contact@compassion-ai.org
Project-URL: Bug Tracker, https://github.com/compassionai/issues
Classifier: Intended Audience :: Science/Research
Classifier: License :: OSI Approved :: GNU General Public License v3 (GPLv3)
Classifier: Programming Language :: Python :: 3.6
Classifier: Topic :: Scientific/Engineering :: Artificial Intelligence
Requires-Python: >=3.6
License-File: LICENSE
Requires-Dist: compassionai-common (>=0.1.0)
Requires-Dist: compassionai-manas (>=0.1.0)
Requires-Dist: compassionai-garland (>=0.1.0)
Requires-Dist: tqdm (>=4.64.1)
